odoo/addons/sm_teletacs/__init__.py
odoo/addons/sm_teletacs/__manifest__.py
odoo/addons/sm_teletacs/models/__init__.py
odoo/addons/sm_teletacs/models/models_smp_teletac.py
odoo/addons/sm_teletacs/security/ir.model.access.csv
odoo/addons/sm_teletacs/views/views_teletac.xml
odoo12_addon_sm_teletacs-12.0.0.0.5.dist-info/METADATA
odoo12_addon_sm_teletacs-12.0.0.0.5.dist-info/WHEEL
odoo12_addon_sm_teletacs-12.0.0.0.5.dist-info/top_level.txt
odoo12_addon_sm_teletacs-12.0.0.0.5.dist-info/RECORD
