Metadata-Version: 2.1
Name: odoo12-addon-sm-teletacs
Version: 12.0.0.0.5
Summary: Create extra expenses for carsharing usages
Home-page: https://www.sommobilitat.coop
Author: Som Mobilitat
License: UNKNOWN
Platform: UNKNOWN
Classifier: Programming Language :: Python
Classifier: Framework :: Odoo
Classifier: Framework :: Odoo :: 12.0
Requires-Python: >=3.5
Requires-Dist: odoo12-addon-sm-partago-usage
Requires-Dist: odoo12-addon-vertical-carsharing
Requires-Dist: odoo (<12.1dev,>=12.0a)
